[
  {
    "type": 1,
    "title": "Guess what word will be inside.",
    "src": "I{?} that TV show for weeks!",
    "answer": "'ve been watching",
    "question": "____ (watch)"
  },
  {
    "type": 1,
    "title": "",
    "src": "I{?} that TV show for weeks!",
    "answer": " have been watching",
    "question": "____ (watch)"
  },
  {
    "type": 2,
    "title": "Arrange sentence.",
    "src": "Who is it?"
  },
  {
    "type": 2,
    "title": "Arrange sentence.",
    "src": "I'm good, thanks."
  }
]
